{"eventCommands":[{"code":111,"indent":0,"parameters":["1","0","0","1","2b9c1eba-e8be-4932-9a79-f37242cc8a11","0","0","0","0","1","0","0","0","0","0","0","0","0","0","0","0","0","0","ce89f973-6ed6-41fc-99d7-e3ca5fc1ce8c","1","661cb624-e856-494e-94b8-0e41064e90b0","51ec1c98-b2b3-49bc-b488-fc945381eaa0","8fd93d41-fb58-401b-8d6b-f7d5396d3fec","0","0","0","0","0","-2","0","0","0","0","0","0","0","0","0","0","0","0","0","0","0","0","0"],"route":[]},{"code":101,"indent":1,"parameters":["1","0","1","0","-1","","犬","犬 - コピー","犬","25542bfa-c069-4b3c-87e3-d2cc02b4fa37"],"route":[]},{"code":401,"indent":2,"parameters":["話は聞かせてもらった、困っている人は見過ごせぬ。","97"],"route":[]},{"code":101,"indent":1,"parameters":["1","0","1","0","-1","","犬","犬 - コピー","犬","25542bfa-c069-4b3c-87e3-d2cc02b4fa37"],"route":[]},{"code":401,"indent":2,"parameters":["俺も協力しよう！","97"],"route":[]},{"code":101,"indent":1,"parameters":["1","0","1","0","-1","","","","",""],"route":[]},{"code":401,"indent":2,"parameters":["犬を仲間にしますか？","97"],"route":[]},{"code":102,"indent":1,"parameters":["2","0","-1","0","1",""],"route":[]},{"code":402,"indent":1,"parameters":["1","97","はい"],"route":[]},{"code":129,"indent":2,"parameters":["25542bfa-c069-4b3c-87e3-d2cc02b4fa37","1","0"],"route":[]},{"code":101,"indent":2,"parameters":["1","0","1","0","-1","","犬","犬 - コピー","犬","25542bfa-c069-4b3c-87e3-d2cc02b4fa37"],"route":[]},{"code":401,"indent":3,"parameters":["よろしく頼む！","97"],"route":[]},{"code":216,"indent":2,"parameters":["0"],"route":[]},{"code":121,"indent":2,"parameters":["0","2b9c1eba-e8be-4932-9a79-f37242cc8a11","1","1"],"route":[]},{"code":214,"indent":2,"parameters":[],"route":[]},{"code":121,"indent":2,"parameters":["0","a0159475-3a24-4710-8db4-5b34f7371b15","1","0"],"route":[]},{"code":0,"indent":2,"parameters":["0","97",""],"route":[]},{"code":402,"indent":1,"parameters":["2","97","いいえ"],"route":[]},{"code":101,"indent":2,"parameters":["1","0","1","0","-1","","犬","犬 - コピー","犬","25542bfa-c069-4b3c-87e3-d2cc02b4fa37"],"route":[]},{"code":401,"indent":3,"parameters":["くぅーん。","97"],"route":[]},{"code":0,"indent":2,"parameters":["0","97",""],"route":[]},{"code":404,"indent":1,"parameters":[],"route":[]},{"code":0,"indent":1,"parameters":[],"route":[]},{"code":411,"indent":0,"parameters":[],"route":[]},{"code":101,"indent":1,"parameters":["1","0","1","0","-1","","犬","犬 - コピー","犬","25542bfa-c069-4b3c-87e3-d2cc02b4fa37"],"route":[]},{"code":401,"indent":2,"parameters":["・・・。","97"],"route":[]},{"code":0,"indent":1,"parameters":[],"route":[]},{"code":412,"indent":0,"parameters":[],"route":[]},{"code":0,"indent":0,"parameters":[],"route":[]}],"id":"b6c603b9-06c7-4e3e-a60c-81aa1168a6a5","page":0,"type":0}