{"assetTypeId":1,"id":"2eeef9a8-dfef-456c-bc66-7b3815f97193","imageSettings":[{"animationFrame":0,"animationSpeed":0,"path":"Other1_028_04.png","sizeX":98,"sizeY":98},{"animationFrame":0,"animationSpeed":0,"path":"Other1_028_04.png","sizeX":0,"sizeY":0},{"animationFrame":0,"animationSpeed":0,"path":"Other1_028_04.png","sizeX":0,"sizeY":0},{"animationFrame":0,"animationSpeed":0,"path":"Other1_028_04.png","sizeX":0,"sizeY":0},{"animationFrame":0,"animationSpeed":0,"path":"Other1_028_04.png","sizeX":0,"sizeY":0}],"name":"オーブ（青、破損）","sort":149,"type":0,"weaponTypeId":0}