{"assetTypeId":1,"id":"4a98cb4a-16e4-4d97-8993-a6276636a13a","imageSettings":[{"animationFrame":0,"animationSpeed":0,"path":"Weapon_019_01.png","sizeX":98,"sizeY":98},{"animationFrame":0,"animationSpeed":0,"path":"Weapon_019_02.png","sizeX":98,"sizeY":98},{"animationFrame":0,"animationSpeed":0,"path":"Weapon_019_03.png","sizeX":98,"sizeY":98},{"animationFrame":0,"animationSpeed":0,"path":"Weapon_019_04.png","sizeX":98,"sizeY":98},{"animationFrame":0,"animationSpeed":0,"path":"Weapon_019_01.png","sizeX":0,"sizeY":0}],"name":"Weapon（杖、小、輝き）","sort":243,"type":0,"weaponTypeId":0}