{"assetTypeId":1,"id":"7e7889e0-c69e-45e0-b3e8-34b234ac21dd","imageSettings":[{"animationFrame":3,"animationSpeed":30,"path":"Vehicle_017.png","sizeX":294,"sizeY":98},{"animationFrame":3,"animationSpeed":30,"path":"Vehicle_018.png","sizeX":294,"sizeY":98},{"animationFrame":3,"animationSpeed":30,"path":"Vehicle_019.png","sizeX":294,"sizeY":98},{"animationFrame":3,"animationSpeed":30,"path":"Vehicle_020.png","sizeX":294,"sizeY":98},{"animationFrame":3,"animationSpeed":30,"path":"Vehicle_017.png","sizeX":294,"sizeY":98}],"name":"Vehicle（ユニコーン）","sort":257,"type":0,"weaponTypeId":0}